pyreq.py
pyreq-1.2.0.dist-info/DESCRIPTION.rst
pyreq-1.2.0.dist-info/METADATA
pyreq-1.2.0.dist-info/RECORD
pyreq-1.2.0.dist-info/WHEEL
pyreq-1.2.0.dist-info/entry_points.txt
pyreq-1.2.0.dist-info/metadata.json
pyreq-1.2.0.dist-info/top_level.txt
