Metadata-Version: 2.0
Name: pyreq
Version: 1.2.0
Summary: A console based http client with syntax higlighting
Home-page: https://github.com/BookOwl/pyreq
Author: Matthew (BookOwl)
Author-email: None
License: MIT
Keywords: web http https curl
Platform: UNKNOWN
Classifier: Development Status :: 4 - Beta
Classifier: Environment :: Console
Classifier: Intended Audience :: Developers
Classifier: Intended Audience :: End Users/Desktop
Classifier: License :: OSI Approved :: MIT License
Classifier: Natural Language :: English
Classifier: Operating System :: OS Independent
Classifier: Topic :: Internet
Classifier: Topic :: Internet :: WWW/HTTP
Classifier: Topic :: Internet :: WWW/HTTP :: Browsers
Classifier: Topic :: Utilities
Requires-Dist: colorama (>=0.3)
Requires-Dist: pygments (>=2.1)
Requires-Dist: requests (>=2.8,<3)
